tqpy/__init__.py
tqpy/utils.py
tqpy/analysis/__init__.py
tqpy/analysis/functions.py
tqpy/analysis/reporter.py
tqpy/analysis/visualizer.py
tqpy-0.3.10.dist-info/DESCRIPTION.rst
tqpy-0.3.10.dist-info/METADATA
tqpy-0.3.10.dist-info/RECORD
tqpy-0.3.10.dist-info/WHEEL
tqpy-0.3.10.dist-info/metadata.json
tqpy-0.3.10.dist-info/top_level.txt
