Metadata-Version: 2.0
Name: tqpy
Version: 0.3.10
Summary: A compact, scalable, statistical analysis, and reporting package built on top of
Home-page: https://www.github.com/notslar-ralston/tqpy
Author: Rashad Alston
Author-email: ralston@yahoo-inc.com
License: BDS 3 Clause
Platform: any
Requires-Dist: bokeh (==0.12.3)
Requires-Dist: matplotlib (>=1.5.2)
Requires-Dist: numpy (>=1.7.1)
Requires-Dist: pandas (>=0.17.1)
